setup.py
komal_indian_states_25/__init__.py
komal_indian_states_25/asgi.py
komal_indian_states_25/settings.py
komal_indian_states_25/urls.py
komal_indian_states_25/wsgi.py
komal_indian_states_25.egg-info/PKG-INFO
komal_indian_states_25.egg-info/SOURCES.txt
komal_indian_states_25.egg-info/dependency_links.txt
komal_indian_states_25.egg-info/requires.txt
komal_indian_states_25.egg-info/top_level.txt
kst1/__init__.py
kst1/admin.py
kst1/apps.py
kst1/fields.py
kst1/forms.py
kst1/models.py
kst1/states.py
kst1/tests.py
kst1/views.py
kst1/migrations/__init__.py